experiment_03_I2S/i2sMaster.v
module i2sMaster#(parameter DATASIZE = 16)(
  input rst,
  //I2S signals
  output BCLK_o, //SCK
  output reg LRCLK, //WS
  output SDATA,
  input BCLK_i, //SCK
  //Data interface
  input [DATASIZE-1:0] rightAudio,
  input [DATASIZE-1:0] leftAudio,
  input enable,
  output reg RightNLeft);
  //Get counter size
  localparam COUNTERSIZE = $clog2(DATASIZE);
  //Current channel
  localparam LEFT = 1'b0, RIGHT = 1'b1;
  //Data buffer to transmit
  reg [DATASIZE-1:0] dataBuff;
  //Update data buff
  wire updatePulse;
  //Count transmitted bits
  reg [COUNTERSIZE-1:0] bitCounter;
  wire bitCounterDone;

  wire BCLK;

  //All BCLKs are same
  assign BCLK = BCLK_i & enable;
  assign BCLK_o = BCLK;

  //Data routing signals
  assign SDATA = dataBuff[DATASIZE-1];
  assign updatePulse = LRCLK ^ RightNLeft;
  always@(negedge BCLK)
    begin
      if(updatePulse)
        dataBuff[DATASIZE-1:0] <= (LRCLK == RIGHT) ? rightAudio : leftAudio;
      else
        dataBuff <= dataBuff << 1;
    end
  
  //Handle LRCLK
  always@(negedge BCLK or posedge rst)
    begin
      if(rst)
        begin
          LRCLK <= LEFT;
        end
      else
        begin
          LRCLK <= (bitCounterDone) ? ~RightNLeft : LRCLK;
        end
    end
  
  //Bit counter
  assign bitCounterDone = bitCounter == (DATASIZE-1);
  always @(negedge BCLK or posedge rst) 
    begin
      if(rst)
        bitCounter <= DATASIZE-1;
      else
        bitCounter <= (bitCounterDone) ? {COUNTERSIZE{1'b0}} : (bitCounter + {{COUNTERSIZE-1{1'b0}}, 1'b1});
    end

  //Actuall channel comes one edge after
  always@(negedge BCLK)
    begin
      RightNLeft <= LRCLK;
    end
endmodule


//PERIOD should be desired output clockperiod in ns and CLKPERIOD should be input clock period in ns.
module bitClkGen #(parameter PERIOD = 651, parameter CLKPERIOD = 10)(
  input clk,
  input rst,
  output reg BCLK);
  localparam CYCLESinHALFP = PERIOD / (2 * CLKPERIOD);
  localparam COUNTERSIZE = $clog2(CYCLESinHALFP-1);

  wire countDone;
  reg [COUNTERSIZE-1:0] counter;

  assign countDone = (counter == (CYCLESinHALFP-1));

  always@(posedge clk or posedge rst)
    begin
      if(rst)
        BCLK <= 1'd0;
      else
        BCLK <= (countDone) ? ~BCLK : BCLK;

    end
  

  always@(posedge clk)
    begin
      if(rst)
          counter <= {COUNTERSIZE{1'd0}};
      else
          counter <= (countDone) ? {COUNTERSIZE{1'd0}} : (counter + {{(COUNTERSIZE-1){1'd0}},1'd1});
    end
endmodule//bitClkGen

experiment_03_I2S/sim.v
`timescale 1ns / 1ps

module i2cMtestbench();
  reg clk, rst, enable;
  wire BCLK,LRCLK, SDATA, RightNLeft;
  reg [15:0] rightAudio, leftAudio;
  
  i2sMaster uut(rst,,LRCLK,SDATA,BCLK,rightAudio,leftAudio,enable,RightNLeft);
  bitClkGen clkgen(clk, rst, BCLK);

  always #5 clk = ~clk;

  

  initial
    begin
      $dumpfile("sim.vcd");
      $dumpvars(0, clk);
      $dumpvars(1, rst);
      $dumpvars(2, enable);
      $dumpvars(3, BCLK);
      $dumpvars(4, LRCLK);
      $dumpvars(5, SDATA);
      $dumpvars(6, RightNLeft);
      $dumpvars(7, rightAudio);
      $dumpvars(8, leftAudio);
      #40000
      $finish;
    end

  initial 
    begin
      clk <= 0;
      rst <= 0;
      rightAudio <= 16'b1010_1010_1010_1010;
      leftAudio <= 16'b1111_0000_1111_0000;
      enable <= 1;
      #16
      rst <= 1;
      #16
      rst <= 0;

    end
endmodule//sim

experiment_03_I2S/simulation/modelsim/sim.vcd
$date
	Thu May 27 23:39:23 2021
$end
$version
	ModelSim Version 2020.1
$end
$timescale
	1ps
$end

$scope module i2cMtestbench $end
$var reg 1 ! clk $end
$var reg 1 " rst $end
$var reg 1 # enable $end
$var wire 1 $ BCLK $end
$var wire 1 % LRCLK $end
$var wire 1 & SDATA $end
$var wire 1 ' RightNLeft $end
$var reg 16 ( rightAudio [15:0] $end
$var reg 16 ) leftAudio [15:0] $end
$upscope $end
$enddefinitions $end
#0
$dumpvars
0!
0"
1#
b1010101010101010 (
b1111000011110000 )
x$
x%
x&
x'
$end
#5000
1!
#10000
0!
#15000
1!
#16000
1"
0$
0%
0'
#20000
0!
#25000
1!
#30000
0!
#32000
0"
#35000
1!
#40000
0!
#45000
1!
#50000
0!
#55000
1!
#60000
0!
#65000
1!
#70000
0!
#75000
1!
#80000
0!
#85000
1!
#90000
0!
#95000
1!
#100000
0!
#105000
1!
#110000
0!
#115000
1!
#120000
0!
#125000
1!
#130000
0!
#135000
1!
#140000
0!
#145000
1!
#150000
0!
#155000
1!
#160000
0!
#165000
1!
#170000
0!
#175000
1!
#180000
0!
#185000
1!
#190000
0!
#195000
1!
#200000
0!
#205000
1!
#210000
0!
#215000
1!
#220000
0!
#225000
1!
#230000
0!
#235000
1!
#240000
0!
#245000
1!
#250000
0!
#255000
1!
#260000
0!
#265000
1!
#270000
0!
#275000
1!
#280000
0!
#285000
1!
#290000
0!
#295000
1!
#300000
0!
#305000
1!
#310000
0!
#315000
1!
#320000
0!
#325000
1!
#330000
0!
#335000
1!
#340000
0!
#345000
1!
1$
#350000
0!
#355000
1!
#360000
0!
#365000
1!
#370000
0!
#375000
1!
#380000
0!
#385000
1!
#390000
0!
#395000
1!
#400000
0!
#405000
1!
#410000
0!
#415000
1!
#420000
0!
#425000
1!
#430000
0!
#435000
1!
#440000
0!
#445000
1!
#450000
0!
#455000
1!
#460000
0!
#465000
1!
#470000
0!
#475000
1!
#480000
0!
#485000
1!
#490000
0!
#495000
1!
#500000
0!
#505000
1!
#510000
0!
#515000
1!
#520000
0!
#525000
1!
#530000
0!
#535000
1!
#540000
0!
#545000
1!
#550000
0!
#555000
1!
#560000
0!
#565000
1!
#570000
0!
#575000
1!
#580000
0!
#585000
1!
#590000
0!
#595000
1!
#600000
0!
#605000
1!
#610000
0!
#615000
1!
#620000
0!
#625000
1!
#630000
0!
#635000
1!
#640000
0!
#645000
1!
#650000
0!
#655000
1!
#660000
0!
#665000
1!
0$
1%
#670000
0!
#675000
1!
#680000
0!
#685000
1!
#690000
0!
#695000
1!
#700000
0!
#705000
1!
#710000
0!
#715000
1!
#720000
0!
#725000
1!
#730000
0!
#735000
1!
#740000
0!
#745000
1!
#750000
0!
#755000
1!
#760000
0!
#765000
1!
#770000
0!
#775000
1!
#780000
0!
#785000
1!
#790000
0!
#795000
1!
#800000
0!
#805000
1!
#810000
0!
#815000
1!
#820000
0!
#825000
1!
#830000
0!
#835000
1!
#840000
0!
#845000
1!
#850000
0!
#855000
1!
#860000
0!
#865000
1!
#870000
0!
#875000
1!
#880000
0!
#885000
1!
#890000
0!
#895000
1!
#900000
0!
#905000
1!
#910000
0!
#915000
1!
#920000
0!
#925000
1!
#930000
0!
#935000
1!
#940000
0!
#945000
1!
#950000
0!
#955000
1!
#960000
0!
#965000
1!
#970000
0!
#975000
1!
#980000
0!
#985000
1!
1$
#990000
0!
#995000
1!
#1000000
0!
#1005000
1!
#1010000
0!
#1015000
1!
#1020000
0!
#1025000
1!
#1030000
0!
#1035000
1!
#1040000
0!
#1045000
1!
#1050000
0!
#1055000
1!
#1060000
0!
#1065000
1!
#1070000
0!
#1075000
1!
#1080000
0!
#1085000
1!
#1090000
0!
#1095000
1!
#1100000
0!
#1105000
1!
#1110000
0!
#1115000
1!
#1120000
0!
#1125000
1!
#1130000
0!
#1135000
1!
#1140000
0!
#1145000
1!
#1150000
0!
#1155000
1!
#1160000
0!
#1165000
1!
#1170000
0!
#1175000
1!
#1180000
0!
#1185000
1!
#1190000
0!
#1195000
1!
#1200000
0!
#1205000
1!
#1210000
0!
#1215000
1!
#1220000
0!
#1225000
1!
#1230000
0!
#1235000
1!
#1240000
0!
#1245000
1!
#1250000
0!
#1255000
1!
#1260000
0!
#1265000
1!
#1270000
0!
#1275000
1!
#1280000
0!
#1285000
1!
#1290000
0!
#1295000
1!
#1300000
0!
#1305000
1!
0$
1&
1'
#1310000
0!
#1315000
1!
#1320000
0!
#1325000
1!
#1330000
0!
#1335000
1!
#1340000
0!
#1345000
1!
#1350000
0!
#1355000
1!
#1360000
0!
#1365000
1!
#1370000
0!
#1375000
1!
#1380000
0!
#1385000
1!
#1390000
0!
#1395000
1!
#1400000
0!
#1405000
1!
#1410000
0!
#1415000
1!
#1420000
0!
#1425000
1!
#1430000
0!
#1435000
1!
#1440000
0!
#1445000
1!
#1450000
0!
#1455000
1!
#1460000
0!
#1465000
1!
#1470000
0!
#1475000
1!
#1480000
0!
#1485000
1!
#1490000
0!
#1495000
1!
#1500000
0!
#1505000
1!
#1510000
0!
#1515000
1!
#1520000
0!
#1525000
1!
#1530000
0!
#1535000
1!
#1540000
0!
#1545000
1!
#1550000
0!
#1555000
1!
#1560000
0!
#1565000
1!
#1570000
0!
#1575000
1!
#1580000
0!
#1585000
1!
#1590000
0!
#1595000
1!
#1600000
0!
#1605000
1!
#1610000
0!
#1615000
1!
#1620000
0!
#1625000
1!
1$
#1630000
0!
#1635000
1!
#1640000
0!
#1645000
1!
#1650000
0!
#1655000
1!
#1660000
0!
#1665000
1!
#1670000
0!
#1675000
1!
#1680000
0!
#1685000
1!
#1690000
0!
#1695000
1!
#1700000
0!
#1705000
1!
#1710000
0!
#1715000
1!
#1720000
0!
#1725000
1!
#1730000
0!
#1735000
1!
#1740000
0!
#1745000
1!
#1750000
0!
#1755000
1!
#1760000
0!
#1765000
1!
#1770000
0!
#1775000
1!
#1780000
0!
#1785000
1!
#1790000
0!
#1795000
1!
#1800000
0!
#1805000
1!
#1810000
0!
#1815000
1!
#1820000
0!
#1825000
1!
#1830000
0!
#1835000
1!
#1840000
0!
#1845000
1!
#1850000
0!
#1855000
1!
#1860000
0!
#1865000
1!
#1870000
0!
#1875000
1!
#1880000
0!
#1885000
1!
#1890000
0!
#1895000
1!
#1900000
0!
#1905000
1!
#1910000
0!
#1915000
1!
#1920000
0!
#1925000
1!
#1930000
0!
#1935000
1!
#1940000
0!
#1945000
1!
0$
0&
#1950000
0!
#1955000
1!
#1960000
0!
#1965000
1!
#1970000
0!
#1975000
1!
#1980000
0!
#1985000
1!
#1990000
0!
#1995000
1!
#2000000
0!
#2005000
1!
#2010000
0!
#2015000
1!
#2020000
0!
#2025000
1!
#2030000
0!
#2035000
1!
#2040000
0!
#2045000
1!
#2050000
0!
#2055000
1!
#2060000
0!
#2065000
1!
#2070000
0!
#2075000
1!
#2080000
0!
#2085000
1!
#2090000
0!
#2095000
1!
#2100000
0!
#2105000
1!
#2110000
0!
#2115000
1!
#2120000
0!
#2125000
1!
#2130000
0!
#2135000
1!
#2140000
0!
#2145000
1!
#2150000
0!
#2155000
1!
#2160000
0!
#2165000
1!
#2170000
0!
#2175000
1!
#2180000
0!
#2185000
1!
#2190000
0!
#2195000
1!
#2200000
0!
#2205000
1!
#2210000
0!
#2215000
1!
#2220000
0!
#2225000
1!
#2230000
0!
#2235000
1!
#2240000
0!
#2245000
1!
#2250000
0!
#2255000
1!
#2260000
0!
#2265000
1!
1$
#2270000
0!
#2275000
1!
#2280000
0!
#2285000
1!
#2290000
0!
#2295000
1!
#2300000
0!
#2305000
1!
#2310000
0!
#2315000
1!
#2320000
0!
#2325000
1!
#2330000
0!
#2335000
1!
#2340000
0!
#2345000
1!
#2350000
0!
#2355000
1!
#2360000
0!
#2365000
1!
#2370000
0!
#2375000
1!
#2380000
0!
#2385000
1!
#2390000
0!
#2395000
1!
#2400000
0!
#2405000
1!
#2410000
0!
#2415000
1!
#2420000
0!
#2425000
1!
#2430000
0!
#2435000
1!
#2440000
0!
#2445000
1!
#2450000
0!
#2455000
1!
#2460000
0!
#2465000
1!
#2470000
0!
#2475000
1!
#2480000
0!
#2485000
1!
#2490000
0!
#2495000
1!
#2500000
0!
#2505000
1!
#2510000
0!
#2515000
1!
#2520000
0!
#2525000
1!
#2530000
0!
#2535000
1!
#2540000
0!
#2545000
1!
#2550000
0!
#2555000
1!
#2560000
0!
#2565000
1!
#2570000
0!
#2575000
1!
#2580000
0!
#2585000
1!
0$
1&
#2590000
0!
#2595000
1!
#2600000
0!
#2605000
1!
#2610000
0!
#2615000
1!
#2620000
0!
#2625000
1!
#2630000
0!
#2635000
1!
#2640000
0!
#2645000
1!
#2650000
0!
#2655000
1!
#2660000
0!
#2665000
1!
#2670000
0!
#2675000
1!
#2680000
0!
#2685000
1!
#2690000
0!
#2695000
1!
#2700000
0!
#2705000
1!
#2710000
0!
#2715000
1!
#2720000
0!
#2725000
1!
#2730000
0!
#2735000
1!
#2740000
0!
#2745000
1!
#2750000
0!
#2755000
1!
#2760000
0!
#2765000
1!
#2770000
0!
#2775000
1!
#2780000
0!
#2785000
1!
#2790000
0!
#2795000
1!
#2800000
0!
#2805000
1!
#2810000
0!
#2815000
1!
#2820000
0!
#2825000
1!
#2830000
0!
#2835000
1!
#2840000
0!
#2845000
1!
#2850000
0!
#2855000
1!
#2860000
0!
#2865000
1!
#2870000
0!
#2875000
1!
#2880000
0!
#2885000
1!
#2890000
0!
#2895000
1!
#2900000
0!
#2905000
1!
1$
#2910000
0!
#2915000
1!
#2920000
0!
#2925000
1!
#2930000
0!
#2935000
1!
#2940000
0!
#2945000
1!
#2950000
0!
#2955000
1!
#2960000
0!
#2965000
1!
#2970000
0!
#2975000
1!
#2980000
0!
#2985000
1!
#2990000
0!
#2995000
1!
#3000000
0!
#3005000
1!
#3010000
0!
#3015000
1!
#3020000
0!
#3025000
1!
#3030000
0!
#3035000
1!
#3040000
0!
#3045000
1!
#3050000
0!
#3055000
1!
#3060000
0!
#3065000
1!
#3070000
0!
#3075000
1!
#3080000
0!
#3085000
1!
#3090000
0!
#3095000
1!
#3100000
0!
#3105000
1!
#3110000
0!
#3115000
1!
#3120000
0!
#3125000
1!
#3130000
0!
#3135000
1!
#3140000
0!
#3145000
1!
#3150000
0!
#3155000
1!
#3160000
0!
#3165000
1!
#3170000
0!
#3175000
1!
#3180000
0!
#3185000
1!
#3190000
0!
#3195000
1!
#3200000
0!
#3205000
1!
#3210000
0!
#3215000
1!
#3220000
0!
#3225000
1!
0$
0&
#3230000
0!
#3235000
1!
#3240000
0!
#3245000
1!
#3250000
0!
#3255000
1!
#3260000
0!
#3265000
1!
#3270000
0!
#3275000
1!
#3280000
0!
#3285000
1!
#3290000
0!
#3295000
1!
#3300000
0!
#3305000
1!
#3310000
0!
#3315000
1!
#3320000
0!
#3325000
1!
#3330000
0!
#3335000
1!
#3340000
0!
#3345000
1!
#3350000
0!
#3355000
1!
#3360000
0!
#3365000
1!
#3370000
0!
#3375000
1!
#3380000
0!
#3385000
1!
#3390000
0!
#3395000
1!
#3400000
0!
#3405000
1!
#3410000
0!
#3415000
1!
#3420000
0!
#3425000
1!
#3430000
0!
#3435000
1!
#3440000
0!
#3445000
1!
#3450000
0!
#3455000
1!
#3460000
0!
#3465000
1!
#3470000
0!
#3475000
1!
#3480000
0!
#3485000
1!
#3490000
0!
#3495000
1!
#3500000
0!
#3505000
1!
#3510000
0!
#3515000
1!
#3520000
0!
#3525000
1!
#3530000
0!
#3535000
1!
#3540000
0!
#3545000
1!
1$
#3550000
0!
#3555000
1!
#3560000
0!
#3565000
1!
#3570000
0!
#3575000
1!
#3580000
0!
#3585000
1!
#3590000
0!
#3595000
1!
#3600000
0!
#3605000
1!
#3610000
0!
#3615000
1!
#3620000
0!
#3625000
1!
#3630000
0!
#3635000
1!
#3640000
0!
#3645000
1!
#3650000
0!
#3655000
1!
#3660000
0!
#3665000
1!
#3670000
0!
#3675000
1!
#3680000
0!
#3685000
1!
#3690000
0!
#3695000
1!
#3700000
0!
#3705000
1!
#3710000
0!
#3715000
1!
#3720000
0!
#3725000
1!
#3730000
0!
#3735000
1!
#3740000
0!
#3745000
1!
#3750000
0!
#3755000
1!
#3760000
0!
#3765000
1!
#3770000
0!
#3775000
1!
#3780000
0!
#3785000
1!
#3790000
0!
#3795000
1!
#3800000
0!
#3805000
1!
#3810000
0!
#3815000
1!
#3820000
0!
#3825000
1!
#3830000
0!
#3835000
1!
#3840000
0!
#3845000
1!
#3850000
0!
#3855000
1!
#3860000
0!
#3865000
1!
0$
1&
